src/__init__.py
src/button.py
src/cli.py
src/client.py
src/client_connection.py
src/constants.py
src/gamestate.py
src/server.py
src/assets/Background.png
src/assets/Facon.ttf
src/assets/font.ttf
src/assets/menu.ttf
src/assets/play.png
src/assets/quit.png
eatemall-0.0.16.dist-info/METADATA
eatemall-0.0.16.dist-info/WHEEL
eatemall-0.0.16.dist-info/entry_points.txt
eatemall-0.0.16.dist-info/top_level.txt
eatemall-0.0.16.dist-info/RECORD
