Metadata-Version: 2.1
Name: eatemall
Version: 0.0.16
Summary: (CLI package to run the server and connect a client to play a multiplayer game!)
Home-page: https://github.com/Jaskaran96/MultiplayerGame
Author: Jaskaran_Singh/Harsh_Singh
Author-email: jaskaran_malhotra@yahoo.in
License: UNKNOWN
Platform: UNKNOWN
Classifier: Programming Language :: Python :: 3
Classifier: Operating System :: OS Independent
Requires-Python: >=3.6
Requires-Dist: pygame
